updownapp/__init__.py
updownapp/app.py
updownapp-0.1.0.dist-info/METADATA
updownapp-0.1.0.dist-info/WHEEL
updownapp-0.1.0.dist-info/entry_points.txt
updownapp-0.1.0.dist-info/top_level.txt
updownapp-0.1.0.dist-info/RECORD
