Metadata-Version: 2.2
Name: updownapp
Version: 0.1.0
Summary: A minimal HTTP file transfer server
Home-page: https://github.com/aesuli/updownapp
Author: Andrea Esuli
Author-email: andrea@esuli.it
License: BSD
Project-URL: Bug Reports, https://github.com/aesuli/updownapp/issues
Project-URL: Source, https://github.com/aesuli/updownapp/
Classifier: Programming Language :: Python :: 3
Classifier: License :: OSI Approved :: BSD License
Classifier: Operating System :: OS Independent
Requires-Python: >=3.8
Requires-Dist: CherryPy==18.10.0
Dynamic: author
Dynamic: author-email
Dynamic: classifier
Dynamic: description
Dynamic: description-content-type
Dynamic: home-page
Dynamic: license
Dynamic: project-url
Dynamic: requires-dist
Dynamic: requires-python
Dynamic: summary
